octopy/Report.py
octopy/__init__.py
octopy/pipeline.py
octopy/prep.py
octopy/selector.py
octopy/smart_EDA.py
octopyx-1.0.0.dist-info/LICENSE
octopyx-1.0.0.dist-info/METADATA
octopyx-1.0.0.dist-info/WHEEL
octopyx-1.0.0.dist-info/top_level.txt
octopyx-1.0.0.dist-info/RECORD
